{
	"name":  "Doctor Simio",
	"bio": "Todo inicia cuando...",
	"thumbnail": "foto-chiquita",
	"cover": "foto-portada",
	"records": [
		{
			"name": "Invasion de gatos",
			"tracks": [
				{
					"name": "Perdon lucho",
					"file": "perdon-lucho.mp3"
				},
				{
					"name": "Hay videos de tu abuelo pensando lo mismo",
					"file": "hay-videos.mp3"
				}
			]
		}
	],
	"video": "link-video",
	"links": [
		{
			"name": "Facebook",
			"url": "http...."
		},
		{
			"name": "Vimeo",
			"url": "http..."
		},
		{
			"name": "Tienda",
			"url": "http..."
		}
	],
	"ciudad": "Bahía Blanca"
}
